{
    "user1": [
        {
            "chat_id": "406626012",
            "username": "Razmanov666",
            "first_name": "Алексей",
            "last_name": "Разманов",
            "status": "reg123"
        }
    ],
    "user2": [
        {
            "chat_id": "1040314362",
            "username": "NikitaNeilko8",
            "first_name": "NIkita",
            "last_name": "Neilko",
            "status": "reg12142"
        }
    ],
    "user3": [
        {
            "chat_id": "428379271",
            "username": "sokurq",
            "first_name": "sokur",
            "last_name": "sokur",
            "status": "reg12142"
        }
    ],
    "user4": [
        {
            "chat_id": "262513320",
            "username": "ekaterinasprin",
            "first_name": "Екатерина",
            "last_name": "",
            "status": "reg12142"
        }
    ],
    "user5": [
        {
            "chat_id": "465843439",
            "username": "",
            "first_name": "God",
            "last_name": "Afrodita",
            "status": "reg12142"
        }
    ]
}